nuc/__init__.py
nuc/builder.py
nuc/envelope.py
nuc/nilauth.py
nuc/payer.py
nuc/policy.py
nuc/selector.py
nuc/token.py
nuc/validate.py
nuc/proto/tx_pb2.py
nuc/proto/tx_pb2.pyi
nuc-0.1.0.dist-info/licenses/LICENSE
nuc-0.1.0.dist-info/METADATA
nuc-0.1.0.dist-info/WHEEL
nuc-0.1.0.dist-info/top_level.txt
nuc-0.1.0.dist-info/RECORD
