Metadata-Version: 2.4
Name: nuc
Version: 0.1.0
Summary: Data structures and functionalities for the Nillion Network user identity and authorization framework.
License: MIT
Project-URL: Repository, https://github.com/nillionnetwork/nuc-py
Project-URL: Documentation, https://nuc.readthedocs.io
Requires-Python: >=3.9
License-File: LICENSE
Requires-Dist: cosmpy==0.9.2
Requires-Dist: requests==2.32.3
Requires-Dist: secp256k1==0.14.0
Provides-Extra: docs
Requires-Dist: myst-parser==2.0.0; extra == "docs"
Requires-Dist: toml~=0.10.2; extra == "docs"
Requires-Dist: sphinx~=7.1; extra == "docs"
Requires-Dist: sphinx-rtd-theme~=2.0.0; extra == "docs"
Provides-Extra: test
Requires-Dist: pytest~=8.2; extra == "test"
Requires-Dist: pytest-cov~=5.0; extra == "test"
Provides-Extra: lint
Requires-Dist: ruff==0.7.0; extra == "lint"
Requires-Dist: pylint~=3.2.0; extra == "lint"
Requires-Dist: pyright==1.1.396; extra == "lint"
Provides-Extra: coveralls
Requires-Dist: coveralls~=4.0; extra == "coveralls"
Provides-Extra: publish
Requires-Dist: build~=0.10; extra == "publish"
Requires-Dist: twine~=4.0; extra == "publish"
Dynamic: license-file
